cloudpayments/__init__.py
cloudpayments/client.py
cloudpayments/enums.py
cloudpayments/errors.py
cloudpayments/models.py
cloudpayments/tests.py
cloudpayments/utils.py
cloudpayments-1.6.0.dist-info/LICENSE
cloudpayments-1.6.0.dist-info/METADATA
cloudpayments-1.6.0.dist-info/WHEEL
cloudpayments-1.6.0.dist-info/top_level.txt
cloudpayments-1.6.0.dist-info/RECORD
