Metadata-Version: 2.1
Name: cloudpayments
Version: 1.6.0
Summary: CloudPayments Python Client Library
Home-page: https://github.com/antidasoftware/cloudpayments-python-client
Author: Antida software
Author-email: info@antidasoftware.com
License: MIT license
Download-URL: https://github.com/antidasoftware/cloudpayments-python-client/tarball/1.6.0
Platform: UNKNOWN
Classifier: Development Status :: 4 - Beta
Classifier: Intended Audience :: Developers
Classifier: License :: OSI Approved :: MIT License
Classifier: Programming Language :: Python
Classifier: Programming Language :: Python :: 2
Classifier: Programming Language :: Python :: 2.7
Classifier: Programming Language :: Python :: 3
Classifier: Programming Language :: Python :: 3.4
Classifier: Programming Language :: Python :: 3.5
Classifier: Programming Language :: Python :: 3.6
Classifier: Programming Language :: Python :: 3.7
Classifier: Topic :: Office/Business
Classifier: Topic :: Office/Business :: Financial
Classifier: Topic :: Software Development :: Libraries :: Python Modules
Requires: requests (>=2.9.1)
Requires: pytz (>=2015.7)
Requires-Dist: requests (>=2.9.1)
Requires-Dist: pytz (>=2015.7)
